confusable_homoglyphs/__init__.py
confusable_homoglyphs/_version.py
confusable_homoglyphs/categories.json
confusable_homoglyphs/categories.py
confusable_homoglyphs/cli.py
confusable_homoglyphs/confusables.json
confusable_homoglyphs/confusables.py
confusable_homoglyphs/utils.py
confusable_homoglyphs-3.3.0.dist-info/AUTHORS.rst
confusable_homoglyphs-3.3.0.dist-info/LICENSE
confusable_homoglyphs-3.3.0.dist-info/METADATA
confusable_homoglyphs-3.3.0.dist-info/WHEEL
confusable_homoglyphs-3.3.0.dist-info/entry_points.txt
confusable_homoglyphs-3.3.0.dist-info/top_level.txt
confusable_homoglyphs-3.3.0.dist-info/RECORD
