Metadata-Version: 2.1
Name: confusable-homoglyphs
Version: 3.3.0
Summary: Detect confusable usage of unicode homoglyphs, prevent homograph attacks.
Home-page: https://github.com/vhf/confusable_homoglyphs
Author: Victor Felder
Author-email: victorfelder@gmail.com
License: MIT
Keywords: confusable,homoglyph,attack,homograph,unicode,spoofing
Classifier: Development Status :: 5 - Production/Stable
Classifier: Intended Audience :: Developers
Classifier: License :: OSI Approved :: MIT License
Classifier: Natural Language :: English
Classifier: Programming Language :: Python :: 3
Classifier: Programming Language :: Python :: 3.7
Classifier: Programming Language :: Python :: 3.8
Classifier: Programming Language :: Python :: 3.9
Classifier: Programming Language :: Python :: 3.10
Classifier: Programming Language :: Python :: 3.11
Classifier: Programming Language :: Python :: 3.12
Classifier: Topic :: Text Processing :: Filters
Classifier: Topic :: Text Processing
Classifier: Topic :: Utilities
License-File: LICENSE
License-File: AUTHORS.rst
Provides-Extra: cli
Requires-Dist: click ; extra == 'cli'
